{
    "images": [
        {
            "url": "https://bds123.cdn.static123.com/images/thumbs/900x600/fit/2023/05/08/fb-img-1683532701488_1683532738.jpg",
            "public_id": ""
        }
    ],
    "title": "Mua Bán Căn Hộ, Nhà Chung Cư Toàn Quốc Giá Rẻ 2023",
    "body": [
        {
            "header": "Chính chủ bán Căn hộ 80m2 Tập thể Nguyên Hồng 4 phòng ngủ cực hiếm",
            "address": "Địa chỉ: Đường Nguyên Hồng, Phường Láng Hạ, Quận Đống Đa, Hà Nội",
            "attributes": [
                {
                    "price": "2.516 tỷ",
                    "acreage": "80",
                    "bedroom": "4",
                    "bathroom": "2",
                    "published": "1 giờ trước"
                }
            ],
            "images": [
                "https://bds123.cdn.static123.com/images/thumbs/900x600/fit/2023/05/08/5c66f33e-20e1-4fed-81f8-5bb1a0d6530f_1683531782.jpg",
                "https://bds123.cdn.static123.com/images/thumbs/900x600/fit/2023/05/08/aeb360a5-edde-4667-a7b2-986afff00807_1683531782.jpg",
                "https://bds123.cdn.static123.com/images/thumbs/900x600/fit/2023/05/08/712ded82-8864-4e2e-a6f0-225d25497498_1683531797.jpg",
                "https://bds123.cdn.static123.com/images/thumbs/900x600/fit/2023/05/08/ebede96e-9de7-451d-b638-1bc51c445783_1683531795.jpg"
            ],
            "sumaryPost": {
                "header": "Tóm tắt tin đăng",
                "content": "Anh/chị Mạnh Quốc SĐT: 0989051997 Bán căn hộ Đường Nguyên Hồng, Phường Láng Hạ, Quận Đống Đa, Hà Nội giá 2.516 tỷ, diện tích: 80m2, thiết kế: 4PN- 2WC."
            },
            "description": {
                "header": "Thông tin mô tả",
                "content": "Thông tin mô tả:  Nhà tập thể Đại học Luật mặt đường Nguyên hồng, tầng 5 đã cơi nới thêm một tầng 6.  Diện tích sử dụng 80m, gồm 1 khách 1 bếp 4 ngủ 2wc. Trong đó có 1 ngủ 20m, 2 ngủ 15m, 1 ngủ 11m, các phòng đều có cửa sổ và ánh sáng!  Bếp thoáng, có sân thượng để trồng vườn hoặc rau xanh  Nhà mới sơn sửa chưa có người vào ở.  Vị trí thuận tiện, khu dân cư đông vui sầm uất nhưng vô cùng thoáng khí nhiều cây xanh môi trường tốt!  Đi bộ 20m sang chợ, gần trường tiểu học tiểu học Nam thành công, Trung học phổ thông Phan Huy Chú, đi sang Nguyễn Chí Thanh thì vô vàn trường Đại học: Luật, Ngoại Giao, Công đoàn....vv, gần trung tâm thương mại và rạp chiếu phim....vv và vân mây, các hướng đi đều tiện!  Sổ đỏ 32.7m  Giá 2ti516. Chính chủ.  Có Trung gian.  Miễn đăng tin quảng cáo.  Đt: 0989051997"
            },
            "post_characteristic": {
                "header": "Đặc điểm tin đăng",
                "content": [
                    { "name": "Mã tin đăng:", "content": "647016" },
                    { "name": "Khu vực:", "content": "Quận Đống Đa,  Hà Nội" },
                    { "name": "Gói tin:", "content": "Tin VIP Đặc biệt" },
                    {
                        "name": "Ngày bắt đầu:",
                        "content": "Thứ hai, 15:06 08/05/2023"
                    },
                    {
                        "name": "Ngày hết hạn:",
                        "content": "Thứ năm, 15:06 18/05/2023"
                    }
                ]
            },
            "userPost": {
                "name": "Mạnh Quốc",
                "phone": "0989051997",
                "zalo": "https://bds123.vn/0989051997"
            }
        },
        {
            "header": "Bán chung cư dự án Ventoso Tower chính chủ, full nội thất, giá cắt lỗ chỉ còn 1,2 tỷ",
            "address": "Địa chỉ: Ventoso Tower - Đường ĐT 743C, Phường Tân Đông Hiệp, Thành Phố Dĩ An, Bình Dương",
            "attributes": [
                {
                    "price": "1.2 tỷ",
                    "acreage": "40",
                    "bedroom": "1",
                    "bathroom": "1",
                    "published": "9 phút trước"
                }
            ],
            "images": [
                "https://bds123.cdn.static123.com/images/thumbs/900x600/fit/2023/04/27/mua-ban-can-ho-ventoso-tower-2_1682588385.jpg",
                "https://bds123.cdn.static123.com/images/thumbs/900x600/fit/2023/04/27/mua-ban-can-ho-ventoso-tower-1_1682588385.jpg",
                "https://bds123.cdn.static123.com/images/thumbs/900x600/fit/2023/04/27/mua-ban-can-ho-ventoso-tower_1682588385.jpg"
            ],
            "sumaryPost": {
                "header": "Tóm tắt tin đăng",
                "content": "Anh/chị Huỳnh Trung Nghĩa SĐT: Huỳnh Trung Nghĩa Bán căn hộ Ventoso Tower, Dĩ An giá 1.2 tỷ tại Bình Dương, diện tích: 40m2, thiết kế: 1PN- 1WC."
            },
            "description": {
                "header": "Thông tin mô tả",
                "content": "Căn hộ Ventoso Tower cần bán gấp với giá 1,2 tỷ đồng, giá này đã giảm 150 triệu so với giá mua ban đầu là 1,35 tỷ đồng. Chủ sở hữu đã hoàn thiện nội thất trong căn hộ, nên người mua không phải lo lắng về vấn đề này.  Căn hộ nằm tại vị trí đắc địa, ngay đường Tỉnh lộ 743B và 743C. Cách trung tâm mua sắm Vincom Dĩ An chỉ 600m, cách chợ Dĩ An chỉ 800m, cách bệnh viện Becamex khoảng 2km và cách trung tâm Thủ Đức 4km. Đi đến trung tâm quận 1 chỉ mất khoảng 16km.  Căn hộ có diện tích 40m², bao gồm 1 phòng ngủ, 1 phòng tắm, 1 phòng khách và đặc biệt có một Logia rộng rãi.  Giá để lại cho căn hộ là 1,2 tỷ đồng và bao gồm cả nội thất và phí. Vui lòng liên hệ với chính chủ qua số điện thoại 0799 382 527 để biết thêm chi tiết."
            },
            "post_characteristic": {
                "header": "Đặc điểm tin đăng",
                "content": [
                    { "name": "Mã tin đăng:", "content": "640897" },
                    {
                        "name": "Khu vực:",
                        "content": "Thành Phố Dĩ An,  Bình Dương"
                    },
                    { "name": "Dự án:", "content": "Ventoso Tower" },
                    { "name": "Gói tin:", "content": "Tin VIP 1" },
                    {
                        "name": "Ngày bắt đầu:",
                        "content": "Thứ năm, 16:40 27/04/2023"
                    },
                    {
                        "name": "Ngày hết hạn:",
                        "content": "Thứ sáu, 16:40 12/05/2023"
                    }
                ]
            },
            "userPost": {
                "name": "Huỳnh Trung Nghĩa",
                "phone": "Huỳnh Trung Nghĩa",
                "zalo": "javascript:void(0);"
            }
        },
        {
            "header": "Bán 100 căn hộ Rica Quận 9 1PN-2PN-3PN. Bán: 1,75 tỷ, cho thuê 5.5triệu/tháng, nhà mới 100%, sổ hồng",
            "address": "Địa chỉ: Ricca - 2 Đường Gò Cát, Phường Phú Hữu, Quận 9, Hồ Chí Minh",
            "attributes": [
                {
                    "price": "1.75 tỷ",
                    "acreage": "56",
                    "bedroom": "1",
                    "bathroom": "1",
                    "published": "8 giờ trước"
                }
            ],
            "images": [
                "https://bds123.cdn.static123.com/images/thumbs/900x600/fit/2023/04/22/cho-thue-ricca-8_1682149289.jpg",
                "https://bds123.cdn.static123.com/images/thumbs/900x600/fit/2023/04/22/phong-ngu-ricca-0914538498-3_1682149295.jpg",
                "https://bds123.cdn.static123.com/images/thumbs/900x600/fit/2023/04/22/cho-thue-ricca-6_1682149287.jpg",
                "https://bds123.cdn.static123.com/images/thumbs/900x600/fit/2023/03/20/cho-thue-ricca-4_1679297251.jpg"
            ],
            "sumaryPost": {
                "header": "Tóm tắt tin đăng",
                "content": "Anh/chị Happy Land SĐT: 0912598058 Bán căn hộ Ricca, Quận 9 giá 1.75 tỷ tại Hồ Chí Minh, diện tích: 56m2, thiết kế: 1PN- 1WC."
            },
            "description": {
                "header": "Thông tin mô tả",
                "content": "❤❤ TIN THẬT - SẢN PHẨM THẬT, TƯ VẤN CHUYÊN NGHIỆP, TẬN T M, HỖ TRỢ VAY, LÀM HỒ SƠ SANG TÊN MIỄN PHÍ  Tọa lạc ngay trung tâm phường Phú Hữu, TP Thủ Đức, cách UBND phường 300m, cách quận 2 chỉ 2km. trong bán kính 1- 4km thu hưởng tất cả các tiện ích chợ, trường học, bệnh viện, siêu thị…  Từ Ricca chỉ 1,5km kết nối lên cao tốc Long Thành Dầu Giây đi về quận 1 hoặc Đồng Nai, Bà Rịa Vũng Tàu… Sống tại Ricca đi làm tại các quận trung tâm, khu công nghệ cao, sân bay Long Thành, cảng… học mẫu giáo, cấp 1, 2, đại học cũng rất thuận tiện.  Dự án Ricca có tổng 572 căn, đầy đủ tiện ích phục vụ nhu cầu sinh hoạt của cư dân: Hồ bơi người lớn và trẻ em: 1200m2; công viên, sinh hoạt cộng đồng, nhà trẻ, siêu thị mini…  BÁN & CHO THUÊ CĂN HỘ RICCA  * 1+1PN = 56m2 - 58m2 từ 1,75 tỷ - 2,2 tỷ  * 2PN = 69m2 - 87m2 = từ 2,48 tỷ - 2,8 tỷ  * 3PN = 112m2 - 118m2 = 3,99 tỷ - 4,3 tỷ  A.xx.02 = 56m2 = 1,75 tỷ (căn giá tốt duy nhất)  A.xx.11 = 56m2 = 2,15 tỷ  A.xx.20 = 52m2 = 1.88 tỷ  A.xx.09 = 56m2 = 2,1 tỷ full nội thất  A.xx.08 = 56m2 = 2,1 tỷ, full nội thất  B.xx.08 = 56m2 = 1,91 tỷ (giá tốt duy nhất)  B.xx.17 = 66,8m2 = 2,4 tỷ (giá tốt duy nhất)  B.16.14 = 58m2 = 1.99 tỷ (làm việc với chủ nhà O914.538.498)  B.05.12 = 56m2 = 1,92 tỷ  B.17.14 = 115m2 = 3,8 tỷ, duplex, sân vườn 18m2 (làm việc với chủ nhà O914.538.498)  A.17.xx = 112m2 = 4,04 tỷ  B.17.xx = 112m2 = 4,6 tỷ  Và nhiều căn khác đầy đủ các tầng, hướng, view, diện tích...  * NHÀ MỚI 100%, CÓ SỔ HỒNG  CHO THUÊ:  * 1+1: 54-56m2: 5.5 - 6 triệu (NT cơ bản) Full nội thất: 7 - 7,5 triệu/ tháng  * 2PN: 67-86m2: 6,5 - 7 triệu (NT cơ bản, gắn rèm), full nội thất: 7,5 triệu - 9 triệu  *3PN duplex: 115m2: 10 - 11 triệu (NT cơ bản), full nội thất 13-15 triệu  $$ XEM THỰC TẾ CĂN HỘ 24/7  $$ HOTLINE: O912.598.O58"
            },
            "post_characteristic": {
                "header": "Đặc điểm tin đăng",
                "content": [
                    { "name": "Mã tin đăng:", "content": "615135" },
                    { "name": "Khu vực:", "content": "Quận 9,  Hồ Chí Minh" },
                    { "name": "Dự án:", "content": "Ricca" },
                    { "name": "Gói tin:", "content": "Tin VIP 1" },
                    {
                        "name": "Ngày bắt đầu:",
                        "content": "Thứ sáu, 08:13 05/05/2023"
                    },
                    {
                        "name": "Ngày hết hạn:",
                        "content": "Thứ hai, 08:13 15/05/2023"
                    }
                ]
            },
            "userPost": {
                "name": "Happy Land",
                "phone": "0912598058",
                "zalo": "https://bds123.vn/0912598058"
            }
        },
        {
            "header": "Chính chủ cần ra gấp bán căn hộ trung tâm giá tốt nhất thị trường, view Landmark 81+ sông Sài Gòn",
            "address": "Địa chỉ: The River Thủ Thiêm - 16 Đường Đại Lộ Vòng Cung, Phường Thủ Thiêm, Quận 2, Hồ Chí Minh",
            "attributes": [
                {
                    "price": "20.5 tỷ",
                    "acreage": "137",
                    "bedroom": "3",
                    "bathroom": "2",
                    "published": "8 giờ trước"
                }
            ],
            "images": [
                "https://bds123.cdn.static123.com/images/thumbs/900x600/fit/2023/03/14/z4178936373381-f427696ce027a234ef4d1e4d303c610d_1678760313.jpg",
                "https://bds123.cdn.static123.com/images/thumbs/900x600/fit/2023/03/14/z4178936377329-bb26363ce4fbff315ae5bce61fbc28e3_1678760312.jpg",
                "https://bds123.cdn.static123.com/images/thumbs/900x600/fit/2023/03/14/z4178936338448-1374167068cba7c4a897c8746a56e96a_1678760312.jpg",
                "https://bds123.cdn.static123.com/images/thumbs/900x600/fit/2023/03/14/z4178936318174-8f8d9385319e2f9656b20b0a4a740f44_1678760311.jpg"
            ],
            "sumaryPost": {
                "header": "Tóm tắt tin đăng",
                "content": "Anh/chị Nguyễn Hoàng Long SĐT: 0798789822 Bán căn hộ The River Thủ Thiêm, Quận 2 giá 20.5 tỷ tại Hồ Chí Minh, hướng: Bắc, diện tích: 137m2, thiết kế: 3PN- 2WC."
            },
            "description": {
                "header": "Thông tin mô tả",
                "content": "Bán căn hộ The River Thủ Thiêm giá tốt nhất thị trường.  Tháp Hudson  Loại 3PN | 125m2  • Căn góc, view thoáng  • Nội thất hoàn thiện cơ bản  • ́ ̂: $ ́  ' Giá bán: 20,5 tỷ  > Ngoài ra em còn rổ hàng đầy đủ các căn 1,2,3,4. Nội thất riêng biệt phù hợp với mọi nhu cầu của khách hàng  ☎️ 0798.789.822 ( Mr.Long)  0364.530.402 ( Ms. Trâm)  ___——____——____——  TỔNG QUAN TIỆN ÍCH THE RIVER  1. Tiện ích ngoài trời  Hồ bơi Olympic 50m  Hồ bơi trẻ em và đài phun nước  ⛱ Ghế tắm nắng và ghế hồ bơi  Buồng tắm đứng ngoài trời  Bãi cỏ  2. Tiện ích trong nhà  ️ Phòng gym, yoga  ️ Phòng Billiards  Phòng chiếu phim  ️ Hệ thống chơi golf trong nhà  Cigar Lounge  Clubhouse  ️ Nhà hàng  Khu thể thao trong nhà  3. Tiện ích liền kề  Bờ sông với chiều dài 100m  Công viên cảnh quan gần 4ha  4. Terrace ngoài trời  Khu ăn uống ngoài trời  River Vista Lounge  Khu chuẩn bị thức ăn  ⛺ Bãi cỏ và khu cắm trại ngoài trời  Ghế cabana  Khu vui chơi trẻ em  ‍‍‍ Khu tiệc nướng BBQ và khu ăn uống ngoài trời dành cho gia đình  ⛓ Thang máy riêng đến khu Terrace"
            },
            "post_characteristic": {
                "header": "Đặc điểm tin đăng",
                "content": [
                    { "name": "Mã tin đăng:", "content": "610804" },
                    { "name": "Khu vực:", "content": "Quận 2,  Hồ Chí Minh" },
                    { "name": "Dự án:", "content": "The River Thủ Thiêm" },
                    { "name": "Gói tin:", "content": "Tin VIP 1" },
                    {
                        "name": "Ngày bắt đầu:",
                        "content": "Thứ bảy, 08:08 15/04/2023"
                    },
                    {
                        "name": "Ngày hết hạn:",
                        "content": "Thứ hai, 08:08 15/05/2023"
                    }
                ]
            },
            "userPost": {
                "name": "Nguyễn Hoàng Long",
                "phone": "0798789822",
                "zalo": "https://bds123.vn/0798789822"
            }
        },
        {
            "header": "Bán chung cư Sol Forest Ecopark chính chủ, tòa SO2, căn 05A giá từ chủ đầu tư",
            "address": "Địa chỉ: Sol Forest Ecopark - Đường Khu đô thị Ecopark, Xã Xuân Quan, Văn Giang, Hưng Yên",
            "attributes": [
                {
                    "price": "Thỏa thuận",
                    "acreage": "103",
                    "bedroom": "3",
                    "bathroom": "2",
                    "published": "9 phút trước"
                }
            ],
            "images": [
                "https://bds123.cdn.static123.com/images/thumbs/900x600/fit/2023/04/24/ban-can-ho-sol-forest-ecopark-3_1682329595.jpg",
                "https://bds123.cdn.static123.com/images/thumbs/900x600/fit/2023/04/24/ban-can-ho-sol-forest-ecopark-2_1682329595.jpg",
                "https://bds123.cdn.static123.com/images/thumbs/900x600/fit/2023/04/24/ban-can-ho-sol-forest-ecopark_1682329594.jpg",
                "https://bds123.cdn.static123.com/images/thumbs/900x600/fit/2023/04/24/ban-can-ho-sol-forest-ecopark-1_1682329594.jpg"
            ],
            "sumaryPost": {
                "header": "Tóm tắt tin đăng",
                "content": "Anh/chị Hà Văn Thơ SĐT: 0988221054 Bán căn hộ Sol Forest Ecopark, Văn Giang giá Thỏa thuận tại Hưng Yên, hướng: Đông Nam, diện tích: 103m2, thiết kế: 3PN- 2WC."
            },
            "description": {
                "header": "Thông tin mô tả",
                "content": "Thông tin chi tiết về căn hộ:  - Mã căn hộ: SO216S05A.  - Diện tích tim tường: 103m², diện tích thông thủy: 94m².  - Căn hộ hướng Đông Nam.  Cư dân tại Sol Forest Ecopark sẽ có cơ hội tận hưởng cuộc sống tiện nghi và hiện đại nhất với hàng ngàn tiện ích tuyệt vời như sau:  - Bể bơi nước mặn 4 mùa trên không, cho bạn trải nghiệm bơi lội trong không gian độc đáo, tương tác với khu sông nước tuyệt đẹp giống như tại biệt thự đảo Dubai thu nhỏ.  - Sảnh đón Sol Forest được bao phủ bởi rừng cây xanh tươi.  - Quảng trường trung tâm với thác nước tràn đầy không khí nhiệt đới, thác đổ từ tầng 3 xuống hồ bơi bốn mùa, giống như một khung cảnh rừng nhiệt đới tràn ngập sức sống.  - Khu vườn công viên và các biệt thự mặt sau tòa nhà được thiết kế cảnh quan như những rừng thông tuyệt đẹp.  - Tuyến phố đi bộ Hàn Quốc với phân khu giải trí, ẩm thực, check-in và mua sắm của tuyến nhà phố Vịnh Đảo dài hơn 2,5km.  - Các trường học đẳng cấp như trường liên cấp quốc tế Chadwick và trường Đại học Anh Quốc BUV danh tiếng thế giới ngay kề bên.  Quý khách có thể liên hệ với tôi qua số điện thoại 0988 221 054 để được hỗ trợ và xem căn hộ 24/7."
            },
            "post_characteristic": {
                "header": "Đặc điểm tin đăng",
                "content": [
                    { "name": "Mã tin đăng:", "content": "638504" },
                    {
                        "name": "Khu vực:",
                        "content": "Huyện Văn Giang,  Hưng Yên"
                    },
                    { "name": "Dự án:", "content": "Sol Forest Ecopark" },
                    { "name": "Gói tin:", "content": "Tin VIP 2" },
                    {
                        "name": "Ngày bắt đầu:",
                        "content": "Thứ hai, 16:47 24/04/2023"
                    },
                    {
                        "name": "Ngày hết hạn:",
                        "content": "Thứ ba, 16:47 09/05/2023"
                    }
                ]
            },
            "userPost": {
                "name": "Hà Văn Thơ",
                "phone": "0988221054",
                "zalo": "javascript:void(0);"
            }
        },
        {
            "header": "Bán căn hộ dự án 9X An Sương, căn 2PN, DT 70m2, giá rẻ chỉ 2,1 tỷ đồng",
            "address": "Địa chỉ: 9X An Sương - 380 Đường Song Hành, Phường Hóc Môn, Huyện Hóc Môn, Hồ Chí Minh",
            "attributes": [
                {
                    "price": "2.1 tỷ",
                    "acreage": "70",
                    "bedroom": "2",
                    "bathroom": "2",
                    "published": "19 phút trước"
                }
            ],
            "images": [
                "https://bds123.cdn.static123.com/images/thumbs/900x600/fit/2023/04/27/mua-ban-can-ho-9x-an-suong-2_1682587923.jpg",
                "https://bds123.cdn.static123.com/images/thumbs/900x600/fit/2023/04/27/mua-ban-can-ho-9x-an-suong-1_1682587923.jpg",
                "https://bds123.cdn.static123.com/images/thumbs/900x600/fit/2023/04/27/mua-ban-can-ho-9x-an-suong_1682587923.jpg"
            ],
            "sumaryPost": {
                "header": "Tóm tắt tin đăng",
                "content": "Anh/chị Huỳnh Hùng SĐT: 0901402873 Bán căn hộ 9X An Sương, Hóc Môn giá 2.1 tỷ tại Hồ Chí Minh, diện tích: 70m2, thiết kế: 2PN- 2WC."
            },
            "description": {
                "header": "Thông tin mô tả",
                "content": "Dự án chung cư 9X An Sương - 2 mặt tiền: Song Hành - QL. 22 (Hóc Môn) là một trong những dự án bất động sản tiêu biểu tại TP. HCM.  Dự án được xây dựng trên mặt tiền đường Song Hành, thuộc Trung tâm Hóc Môn, Huyện Hóc Môn, TPHCM.  Chủ đầu tư của dự án là Tập đoàn Hưng Thịnh và đơn vị xây dựng là Hưng Thịnh Incons.  Quy mô dự án là 9.500m2, gồm 2 block, cao 25 tầng và 1 tầng hầm.  Dự án 9X An Sương sở hữu nhiều tiện ích vượt trội như trung tâm thương mại 2.700m2 là trung tâm thương mại duy nhất trong khu vực, hồ bơi vô cực tràn bờ 3 cấp, công viên, nhà trẻ và Shophouse.  Ngoài ra, cư dân của dự án còn có thể dễ dàng tiếp cận với đại siêu thị Aeon Mall Hóc Môn chỉ cách dự án 500m và các trường học các cấp cách khu căn hộ 1km.  Chợ Hóc Môn và Bến xe An Sương và chợ Đầu mối Hóc Môn cũng chỉ cách dự án 5km và bệnh viện Quốc Tế Xuyên Á cách dự án 3,5km.  Dự án 9X An Sương có chính sách thanh toán linh hoạt, mỗi tháng góp 0,5%/tháng, mua nhà thanh toán bằng lương 5,5 triệu/tháng (không cần vay ngân hàng).  Cung cấp các loại căn hộ như Studio 34m2 - Giá 1.1tỷ, 1PN + 52m2 - Giá 1tỷ6, 2PN 70m2 - Giá 2tỷ1 và 3PN 90m2 - Giá 3tỷ.  Khách hàng chỉ cần đặt chỗ với số tiền 50 triệu/căn sẽ được hưởng chiết khấu ưu đãi cao.  Để biết thêm thông tin và đặt chỗ, quý khách hàng có thể liên hệ hotline: 0901 402 873 - Huỳnh Hùng."
            },
            "post_characteristic": {
                "header": "Đặc điểm tin đăng",
                "content": [
                    { "name": "Mã tin đăng:", "content": "640893" },
                    {
                        "name": "Khu vực:",
                        "content": "Huyện Hóc Môn,  Hồ Chí Minh"
                    },
                    { "name": "Dự án:", "content": "9X An Sương" },
                    { "name": "Gói tin:", "content": "Tin VIP 2" },
                    {
                        "name": "Ngày bắt đầu:",
                        "content": "Thứ năm, 16:32 27/04/2023"
                    },
                    {
                        "name": "Ngày hết hạn:",
                        "content": "Thứ sáu, 16:32 12/05/2023"
                    }
                ]
            },
            "userPost": {
                "name": "Huỳnh Hùng",
                "phone": "0901402873",
                "zalo": "javascript:void(0);"
            }
        },
        {
            "header": "Bán căn hộ Beverly tại dự án Vinhomes Grand Park 2PN giá cắt lỗ chỉ 3,7 tỷ",
            "address": "Địa chỉ: The Beverly - Vinhomes grand park - Đường Nguyễn Xiển, Phường Long Thạnh Mỹ, Quận 9, Hồ Chí Minh",
            "attributes": [
                {
                    "price": "3.7 tỷ",
                    "acreage": "79",
                    "bedroom": "2",
                    "bathroom": "2",
                    "published": "19 phút trước"
                }
            ],
            "images": [
                "https://bds123.cdn.static123.com/images/thumbs/900x600/fit/2023/04/25/ban-can-ho-beverly-vinhomes-grand-park-2_1682415543.jpg",
                "https://bds123.cdn.static123.com/images/thumbs/900x600/fit/2023/04/25/ban-can-ho-beverly-vinhomes-grand-park-1_1682415542.jpg",
                "https://bds123.cdn.static123.com/images/thumbs/900x600/fit/2023/04/25/ban-can-ho-beverly-vinhomes-grand-park_1682415542.jpg"
            ],
            "sumaryPost": {
                "header": "Tóm tắt tin đăng",
                "content": "Anh/chị Huỳnh Thanh Tới SĐT: 0938859821 Bán căn hộ The Beverly - Vinhomes grand park, Quận 9 giá 3.7 tỷ tại Hồ Chí Minh, diện tích: 79m2, thiết kế: 2PN- 2WC."
            },
            "description": {
                "header": "Thông tin mô tả",
                "content": "Chủ nhân cần bán gấp căn hộ 2 phòng ngủ tại dự án The Beverly với giá bán lỗ như sau:  - BE3: giá bán 5.5 tỉ đồng, cắt lỗ 500 triệu đồng.  - BE3: giá bán 5.7 tỉ đồng, cắt lỗ 500 triệu đồng.  - BE1: giá bán 4.9 tỉ đồng, cắt lỗ 400 triệu đồng.  - BE6: giá bán 4.1 tỉ đồng, cắt lỗ 400 triệu đồng.  Khách hàng được thanh toán 15% để sang tên sổ đỏ ngay. Ngoài ra, khách hàng sẽ nhận được Voucher Vinfast trị giá 150 triệu đồng. Nếu cần, khách hàng có thể vay vốn từ ngân hàng với lãi suất hỗ trợ trong 2 năm.  Vui lòng liên hệ A. Tới theo số điện thoại 0938 859 821 để biết thêm chi tiết."
            },
            "post_characteristic": {
                "header": "Đặc điểm tin đăng",
                "content": [
                    { "name": "Mã tin đăng:", "content": "639386" },
                    { "name": "Khu vực:", "content": "Quận 9,  Hồ Chí Minh" },
                    {
                        "name": "Dự án:",
                        "content": "The Beverly - Vinhomes grand park"
                    },
                    { "name": "Gói tin:", "content": "Tin VIP 2" },
                    {
                        "name": "Ngày bắt đầu:",
                        "content": "Thứ ba, 16:39 25/04/2023"
                    },
                    {
                        "name": "Ngày hết hạn:",
                        "content": "Thứ tư, 16:39 10/05/2023"
                    }
                ]
            },
            "userPost": {
                "name": "Huỳnh Thanh Tới",
                "phone": "0938859821",
                "zalo": "javascript:void(0);"
            }
        },
        {
            "header": "Bán căn hộ chung cư Phú Đông Premier căn góc chính chủ, DT 68m2, giá chỉ 2,5 tỷ",
            "address": "Địa chỉ: Phú Đông Premier - 42 Đường Lê Trọng Tấn, Phường An Bình, Thành Phố Dĩ An, Bình Dương",
            "attributes": [
                {
                    "price": "2.5 tỷ",
                    "acreage": "68",
                    "bedroom": "2",
                    "bathroom": "2",
                    "published": "29 phút trước"
                }
            ],
            "images": [
                "https://bds123.cdn.static123.com/images/thumbs/900x600/fit/2023/05/04/mua-ban-can-ho-chung-cu-phu-dong-premier-4_1683192459.jpg",
                "https://bds123.cdn.static123.com/images/thumbs/900x600/fit/2023/05/04/mua-ban-can-ho-chung-cu-phu-dong-premier-3_1683192459.jpg",
                "https://bds123.cdn.static123.com/images/thumbs/900x600/fit/2023/05/04/mua-ban-can-ho-chung-cu-phu-dong-premier-1_1683192459.jpg",
                "https://bds123.cdn.static123.com/images/thumbs/900x600/fit/2023/05/04/mua-ban-can-ho-chung-cu-phu-dong-premier-2_1683192459.jpg"
            ],
            "sumaryPost": {
                "header": "Tóm tắt tin đăng",
                "content": "Anh/chị Dinh Đặng SĐT: 0933552290 Bán căn hộ Phú Đông Premier, Dĩ An giá 2.5 tỷ tại Bình Dương, hướng: Đông Bắc, diện tích: 68m2, thiết kế: 2PN- 2WC."
            },
            "description": {
                "header": "Thông tin mô tả",
                "content": "Với vị trí đắc địa trên trục đường Phạm Văn Đồng, căn hộ này mang lại thuận tiện cho việc di chuyển và kết nối với các khu vực lân cận. Ngoài ra, cư dân tại đây còn được hưởng môi trường sống văn minh, gần gũi với hàng xóm thân thiện.  Căn hộ góc 2 phòng ngủ và 2 toilet được thiết kế với các cửa sổ đón ánh sáng tự nhiên, đem lại không gian sống tươi mới và thoáng đãng. Phòng khách rộng rãi, ban công gắn lưới an toàn và logia giúp cho không gian thêm phong phú và tiện nghi hơn.  Dự án cũng cung cấp tiện ích cho cư dân như hồ bơi nước ấm, phòng tập gym, khu vui chơi trẻ em. Kết hợp với khả năng vay vốn với lãi suất ưu đãi từ Vietcombank, đây là một cơ hội tốt cho các nhà đầu tư hoặc gia đình muốn tìm kiếm một không gian sống tiện nghi và đáng yêu. Giá bán của căn hộ là 2.5 tỷ."
            },
            "post_characteristic": {
                "header": "Đặc điểm tin đăng",
                "content": [
                    { "name": "Mã tin đăng:", "content": "644402" },
                    {
                        "name": "Khu vực:",
                        "content": "Thành Phố Dĩ An,  Bình Dương"
                    },
                    { "name": "Dự án:", "content": "Phú Đông Premier" },
                    { "name": "Gói tin:", "content": "Tin VIP 2" },
                    {
                        "name": "Ngày bắt đầu:",
                        "content": "Thứ năm, 16:28 04/05/2023"
                    },
                    {
                        "name": "Ngày hết hạn:",
                        "content": "Thứ sáu, 16:28 19/05/2023"
                    }
                ]
            },
            "userPost": {
                "name": "Dinh Đặng",
                "phone": "0933552290",
                "zalo": "javascript:void(0);"
            }
        },
        {
            "header": "Bán căn hộ Bcons Polygon 2PN, DT 51m2, giá chính chủ chỉ 1,5 tỷ đồng",
            "address": "Địa chỉ: Bcons Polygon - Đường Bế Văn Đàn, Phường An Bình, Thành Phố Dĩ An, Bình Dương",
            "attributes": [
                {
                    "price": "1.5 tỷ",
                    "acreage": "51",
                    "bedroom": "2",
                    "bathroom": "2",
                    "published": "29 phút trước"
                }
            ],
            "images": [
                "https://bds123.cdn.static123.com/images/thumbs/900x600/fit/2023/04/26/ban-can-ho-chung-cu-du-an-bcons-polygon-2_1682501250.jpg",
                "https://bds123.cdn.static123.com/images/thumbs/900x600/fit/2023/04/26/ban-can-ho-chung-cu-du-an-bcons-polygon_1682501249.jpg",
                "https://bds123.cdn.static123.com/images/thumbs/900x600/fit/2023/04/26/ban-can-ho-chung-cu-du-an-bcons-polygon-1_1682501249.jpg"
            ],
            "sumaryPost": {
                "header": "Tóm tắt tin đăng",
                "content": "Anh/chị PKD SĐT: 0329165998 Bán căn hộ Bcons Polygon, Dĩ An giá 1.5 tỷ tại Bình Dương, hướng: Bắc, diện tích: 51m2, thiết kế: 2PN- 2WC."
            },
            "description": {
                "header": "Thông tin mô tả",
                "content": "Căn hộ Bcons Polygon - dự án thành công thứ 8 của tập đoàn Bcons. Sở hữu vị trí đắc địa ngay cạnh TP Thủ Đức. Chỉ mất 5 phút là đến Đại Lộ Phạm Văn Đồng.  Giỏ hàng bán căn hộ Bcons Polygon bao gồm:  - 1 + 1WC, diện tích 41m², giá từ 1,416 - 1,450 tỷ đã bao gồm VAT.  - 2 + 2WC, diện tích 51m² - 68m², giá từ 1,518 - 1,9 tỷ.  - 3 + 2WC, diện tích 65,65m², giá từ 1,950 - 2 tỷ.  Các căn hộ sẽ được bàn giao với đầy đủ nội thất, bao gồm trần thạch cao, đèn LED, tủ bếp trên dưới, mặt đá bếp, bồn rửa chén, bình nước lọc uống tại vòi, sàn gỗ An Cường, phòng khách ốp gạch bóng kiếng 60*60, kính dán an toàn, ban công cửa kéo lùa di động 2 cánh, và thiết bị nhà vệ sinh đầy đủ với kính tắm đứng.  Căn hộ Bcons Polygon còn được trang bị đầy đủ tiện ích để đáp ứng nhu cầu của cư dân, bao gồm hồ bơi tràn bờ, công viên dạo bộ, ăn uống ngay tại sảnh, nhà trẻ, siêu thị mini và phòng sinh hoạt cộng đồng. Ngoài ra, chỉ trong bán kính 500m, quý cư dân có thể dễ dàng kết nối với chợ, trường học cấp 1, 2, 3, bệnh viện quận Thủ Đức, chợ đầu mối nông sản Thủ Đức và nhiều tiện ích khác.  Liên hệ ngay với phòng kinh doanh của chúng tôi qua số điện thoại 0329 165 998 để biết thêm chi tiết và được tư vấn miễn phí. Cảm ơn quý khách đã quan tâm đến căn hộ Bcons Polygon, chúng tôi cam kết cung cấp thông tin chính xác và sản phẩm thật 100%."
            },
            "post_characteristic": {
                "header": "Đặc điểm tin đăng",
                "content": [
                    { "name": "Mã tin đăng:", "content": "640208" },
                    {
                        "name": "Khu vực:",
                        "content": "Thành Phố Dĩ An,  Bình Dương"
                    },
                    { "name": "Dự án:", "content": "Bcons Polygon" },
                    { "name": "Gói tin:", "content": "Tin VIP 2" },
                    {
                        "name": "Ngày bắt đầu:",
                        "content": "Thứ tư, 16:28 26/04/2023"
                    },
                    {
                        "name": "Ngày hết hạn:",
                        "content": "Thứ năm, 16:28 11/05/2023"
                    }
                ]
            },
            "userPost": {
                "name": "PKD",
                "phone": "0329165998",
                "zalo": "javascript:void(0);"
            }
        },
        {
            "header": "Chuyên bán căn hộ Vinhomes Grand Park Quận 9 giá tốt nhất thị trường",
            "address": "Địa chỉ: The Origami - Vinhomes Grand Park - Đường Phước Thiện, Phường Long Thạnh Mỹ, Quận 9, Hồ Chí Minh",
            "attributes": [
                {
                    "price": "2.45 tỷ",
                    "acreage": "67",
                    "bedroom": "2",
                    "bathroom": "2",
                    "published": "2 giờ trước"
                }
            ],
            "images": [
                "https://bds123.cdn.static123.com/images/thumbs/900x600/fit/2023/03/20/z4189842067688-5ba2386560e669fb9eba94fd830b69b6_1679295950.jpg",
                "https://bds123.cdn.static123.com/images/thumbs/900x600/fit/2023/03/20/z3961360951010-5cce8380a608a66eb8e6a7c2fb39c028_1679295950.jpg",
                "https://bds123.cdn.static123.com/images/thumbs/900x600/fit/2023/03/20/z3961360943936-3ffff1d038d5b1c806b4b40dfc11d05e_1679295950.jpg",
                "https://bds123.cdn.static123.com/images/thumbs/900x600/fit/2023/03/20/z3959260090929-2bd90bc659a739e8d4c7ec57d32d9df1_1679295949.jpg"
            ],
            "sumaryPost": {
                "header": "Tóm tắt tin đăng",
                "content": "Anh/chị Nguyễn Hoàng Long SĐT: 0798789822 Bán căn hộ The Origami - Vinhomes Grand Park, Quận 9 giá 2.45 tỷ tại Hồ Chí Minh, diện tích: 67m2, thiết kế: 2PN- 2WC."
            },
            "description": {
                "header": "Thông tin mô tả",
                "content": "Giỏ hàng chuyển nhượng Origami giá 1PN + giá 1950 tỷ| 2PN 2.550 tỷ  Duy nhất 200 căn giá tốt  Giỏ hàng mua mới căn hộ phân khu Origami Giai đoạn 2 chỉ thanh toán 15% ký Hợp đồng mua bán  Các phân khu S7, S8, S9 đã có lịch nhận nhà, vẫn còn HTLS đến cuối năm 2022.  - Anh/Chị nào đang có nhu cầu sở hữu 1 căn hộ đầy đủ tiện ích của khu đô thị Vinhomes, mà giá lại quá tốt, mua đầu tư cũng lời. Vốn ban đầu chỉ từ 15% - 25% giá trị căn hộ  Ngoài ra thì còn rất nhiều căn view đẹp giá tốt khác đang cần bán. Anh/chị liên hệ trực tiếp bên em để được tư vấn.  LH 0798.789.822 Mr Long để được hổ trợ xem nhà và dự án."
            },
            "post_characteristic": {
                "header": "Đặc điểm tin đăng",
                "content": [
                    { "name": "Mã tin đăng:", "content": "615108" },
                    { "name": "Khu vực:", "content": "Quận 9,  Hồ Chí Minh" },
                    {
                        "name": "Dự án:",
                        "content": "The Origami - Vinhomes Grand Park"
                    },
                    { "name": "Gói tin:", "content": "Tin VIP 2" },
                    {
                        "name": "Ngày bắt đầu:",
                        "content": "Thứ năm, 17:00 27/04/2023"
                    },
                    {
                        "name": "Ngày hết hạn:",
                        "content": "Thứ sáu, 17:00 12/05/2023"
                    }
                ]
            },
            "userPost": {
                "name": "Nguyễn Hoàng Long",
                "phone": "0798789822",
                "zalo": "https://bds123.vn/0798789822"
            }
        },
        {
            "header": "Chủ bán căn hộ Penthouse Ricca quận 2, 115m2 3pn chỉ 3,8 tỷ - Hỗ trợ vay - 0914538498",
            "address": "Địa chỉ: Ricca - 2 Đường Gò Cát, Phường Phú Hữu, Quận 9, Hồ Chí Minh",
            "attributes": [
                {
                    "price": "3.8 tỷ",
                    "acreage": "115",
                    "bedroom": "3",
                    "bathroom": "3",
                    "published": "8 giờ trước"
                }
            ],
            "images": [
                "https://bds123.cdn.static123.com/images/thumbs/900x600/fit/2023/01/07/ho-boi-ricca_1673055940.jpg",
                "https://bds123.cdn.static123.com/images/thumbs/900x600/fit/2023/01/07/cong-vien-ricca_1673055931.jpg",
                "https://bds123.cdn.static123.com/images/thumbs/900x600/fit/2023/01/07/gym-ricca_1673055937.jpg",
                "https://bds123.cdn.static123.com/images/thumbs/900x600/fit/2023/01/07/chinh-chu-ban-ricca_1673055928.jpg"
            ],
            "sumaryPost": {
                "header": "Tóm tắt tin đăng",
                "content": "Anh/chị Chị Hiệp SĐT: 0914538498 Bán căn hộ Ricca, Quận 9 giá 3.8 tỷ tại Hồ Chí Minh, hướng: Đông Bắc, diện tích: 115m2, thiết kế: 3PN- 3WC."
            },
            "description": {
                "header": "Thông tin mô tả",
                "content": "Căn hộ Ricca tọa lạc tại mặt tiền đường 30m, thuộc phường Phú Hữu - trung tâm thành phố Thủ Đức. Vị trí rất thuận lợi với khoảng cách chỉ 5-10 phút đến chợ, trường học và khu liên hợp thể thao quốc gia. Ngoài ra, chỉ mất 20 phút để đến trung tâm tài chính Thủ Thiêm, trường học và bệnh viện quốc tế. Đây là một sự lựa chọn lý tưởng cho những người làm việc tại quận 9, quận 2, quận 1, Bình Thạnh hoặc sân bay quốc tế Long Thành.  Các căn hộ của Ricca mới 100% và được trang bị nội thất cao cấp bao gồm tủ kệ bếp Acrylic, phòng ngủ có sàn gỗ, thiết bị vệ sinh ToTo, video call, cửa chống cháy khóa từ, ...  Ngoài ra, cư dân của Ricca còn có thể tận hưởng các tiện ích nội khu như hồ bơi liên hoàn rộng 1200m2, nhà trẻ chất lượng cao với diện tích 500m2, công viên, BBQ, khu shophouse và sân chơi trẻ em.  Căn hộ cần bán:  ** Căn hộ B.16.14 có diện tích 58m2, gồm 1 phòng ngủ và 1 phòng khách, Căn hộ này có view công viên và các khu biệt thự Khang Điền và Phú Long.  Giá bán là 1.99 tỷ đồng đã bao gồm VAT.  ** Penthouse B.17.14 có diện tích 115m2, trong đó có 18m2 sân vườn được công nhận trên sổ, gồm 3 phòng ngủ và 3 phòng tắm. View công viên và các khu biệt thự Khang Điền và Phú Long. Cư dân có thể tận dụng Sky Garden bên hông nhà.  Giá bán là 3.8 tỷ đồng đã bao gồm VAT.  * Các căn hộ đều có sổ đỏ và hỗ trợ vay đến 70% trong vòng 20 năm. Bạn có thể nhận nhà và ở ngay.  Liên hệ trực tiếp chủ qua sđt 0914.538.498 gặp Chị Hiệp."
            },
            "post_characteristic": {
                "header": "Đặc điểm tin đăng",
                "content": [
                    { "name": "Mã tin đăng:", "content": "383709" },
                    { "name": "Khu vực:", "content": "Quận 9,  Hồ Chí Minh" },
                    { "name": "Dự án:", "content": "Ricca" },
                    { "name": "Gói tin:", "content": "Tin VIP 2" },
                    {
                        "name": "Ngày bắt đầu:",
                        "content": "Thứ sáu, 08:15 05/05/2023"
                    },
                    {
                        "name": "Ngày hết hạn:",
                        "content": "Thứ hai, 08:15 15/05/2023"
                    }
                ]
            },
            "userPost": {
                "name": "Chị Hiệp",
                "phone": "0914538498",
                "zalo": "https://bds123.vn/0914538498"
            }
        },
        {
            "header": "Cắt lỗ 400tr căn 3PN 2VS DT 80m2 full nội thất tại Vin Ocean Park giá chỉ 2,1 tỷ LH 0969 493 294",
            "address": "Địa chỉ: Vinhomes Ocean Park - Xã Đa Tốn, Huyện Gia Lâm, Hà Nội",
            "attributes": [
                {
                    "price": "2.1 tỷ",
                    "acreage": "80",
                    "bedroom": "3",
                    "bathroom": "2",
                    "published": "Hôm nay"
                }
            ],
            "images": [
                "https://bds123.cdn.static123.com/images/thumbs/900x600/fit/2022/11/05/z3695805553047-40c37a8e3b6246c438cf7e6921f6d5ad_1667618105.jpg",
                "https://bds123.cdn.static123.com/images/thumbs/900x600/fit/2022/11/05/z3695805630870-701ca365f59720610f0abb55040cb8d0_1667618108.jpg",
                "https://bds123.cdn.static123.com/images/thumbs/900x600/fit/2022/11/05/z3695805623048-6be9e4ce0de8ecdb790c6ab123ca45ad_1667618108.jpg",
                "https://bds123.cdn.static123.com/images/thumbs/900x600/fit/2022/11/05/z3695805617284-fcfda7f7597bf9dcd1e61c40cdd07bc2_1667618108.jpg"
            ],
            "sumaryPost": {
                "header": "Tóm tắt tin đăng",
                "content": "Anh/chị Nguyễn Văn Quang SĐT: 0969493294 Bán căn hộ Vinhomes Ocean Park, Gia Lâm giá 2.1 tỷ tại Hà Nội, diện tích: 80m2, thiết kế: 3PN- 2WC."
            },
            "description": {
                "header": "Thông tin mô tả",
                "content": "Chính chủ cắt lỗ 400tr bán nhanh căn 3N2VS DT 80m² giá thiện chí 2,1 tỷ tại Vin Ocean Park.  - Thiết kế căn hộ bao gồm 3PN đón ánh sáng tự nhiên, thoáng mát, có 2 logia, 2WC tiện dụng; thiết kế căn hộ rất phù hợp với gia đình đông thành viên.  - Tiện ích như tại khu nghỉ dưỡng: Biển hồ, đường dạo bộ, bãi cát trắng với máy tập thể thao ngoài trời, BBQ... Sau những giờ học tập, làm việc căng thẳng.  - Nội thất: Full nội thất liền tường cao cấp.  - Sổ đỏ cầm tay, sẵn sàng giao dịch, chủ nhà dễ tính.  * Giá bán: 2.1 tỷ (giá bán nhanh trong tuần).  * Xem nhà liên hệ 24/7: 0969 493 294"
            },
            "post_characteristic": {
                "header": "Đặc điểm tin đăng",
                "content": [
                    { "name": "Mã tin đăng:", "content": "550797" },
                    { "name": "Khu vực:", "content": "Huyện Gia Lâm,  Hà Nội" },
                    { "name": "Dự án:", "content": "Vinhomes Ocean Park" },
                    { "name": "Gói tin:", "content": "Tin VIP 2" },
                    {
                        "name": "Ngày bắt đầu:",
                        "content": "Thứ năm, 11:19 04/05/2023"
                    },
                    {
                        "name": "Ngày hết hạn:",
                        "content": "Thứ ba, 11:19 09/05/2023"
                    }
                ]
            },
            "userPost": {
                "name": "Nguyễn Văn Quang",
                "phone": "0969493294",
                "zalo": "https://bds123.vn/0969493294"
            }
        },
        {
            "header": "Bán căn hộ độc quyền Bcons Polaris gần Phạm Văn Đồng giá gốc từ CĐT, LH 0976 990 208",
            "address": "Địa chỉ: Bcons Lê Trọng Tấn - 23 Đường Lê Trọng Tấn, Phường Dĩ An, Thành Phố Dĩ An, Bình Dương",
            "attributes": [
                {
                    "price": "1.86 tỷ",
                    "acreage": "52",
                    "bedroom": "2",
                    "bathroom": "2",
                    "published": "Hôm nay"
                }
            ],
            "images": [
                "https://bds123.cdn.static123.com/images/thumbs/900x600/fit/2023/05/05/mua-ban-chung-cu-bcons-polaris-5_1683280682.jpg",
                "https://bds123.cdn.static123.com/images/thumbs/900x600/fit/2023/05/05/mua-ban-chung-cu-bcons-polaris-3_1683280682.jpg",
                "https://bds123.cdn.static123.com/images/thumbs/900x600/fit/2023/05/05/mua-ban-chung-cu-bcons-polaris-4_1683280682.jpg",
                "https://bds123.cdn.static123.com/images/thumbs/900x600/fit/2023/05/05/mua-ban-chung-cu-bcons-polaris-1_1683280682.jpg"
            ],
            "sumaryPost": {
                "header": "Tóm tắt tin đăng",
                "content": "Anh/chị Trần Thị Mỹ Nga SĐT: 0976990208 Bán căn hộ Bcons Lê Trọng Tấn, Dĩ An giá 1.86 tỷ tại Bình Dương, diện tích: 52m2, thiết kế: 2PN- 2WC."
            },
            "description": {
                "header": "Thông tin mô tả",
                "content": "Bcons Polaris - Căn hộ liền kề Phạm Văn Đồng Thủ Đức giá chỉ từ 1.86 tỷ căn 2PN + 2WC:  - Ngân hàng MBBank hỗ trợ vay lãi suất 0% cho đến khi nhận nhà.  - Chỉ cần thanh toán trước 399 triệu cho đến khi nhận nhà.  - Chính sách ưu đãi giá gốc đợt đầu tiên mở bán từ chủ đầu tư Bcons.  Vị trí đắc địa ngay mặt tiền đường Lê Trọng Tấn, Dĩ An, Bình Dương. Chỉ cách 3 phút là tới đường Phạm Văn Đồng 3, và khoảng 500m tới QL1K và Vành Đai II. Từ đây, bạn cũng có thể dễ dàng di chuyển tới Sân Bay Tân Sơn Nhất trong 18 phút.  - Tiện ích nội khu đa dạng: Trung tâm thương mại, công viên dạo bộ, hồ bơi thư giãn, phòng tập gym, nhà trẻ, ...  - Thiết kế căn hộ thông minh với diện tích từ 40 - 60m² (1 - 2 phòng ngủ).  - Chủ đầu tư Bcons Group uy tín và có năng lực.  - Đặt cọc 30 triệu/căn sẽ được ưu tiên chọn căn đẹp (hoàn lại 100% tiền cọc nếu không mua).  Hãy liên hệ với chúng tôi qua số điện thoại 0976 990 208 (Ms Nga) để xem căn hộ và nhận tư vấn thông tin sớm nhất nhé!"
            },
            "post_characteristic": {
                "header": "Đặc điểm tin đăng",
                "content": [
                    { "name": "Mã tin đăng:", "content": "645136" },
                    {
                        "name": "Khu vực:",
                        "content": "Thành Phố Dĩ An,  Bình Dương"
                    },
                    { "name": "Dự án:", "content": "Bcons Lê Trọng Tấn" },
                    { "name": "Gói tin:", "content": "Tin VIP 2" },
                    {
                        "name": "Ngày bắt đầu:",
                        "content": "Thứ sáu, 16:58 05/05/2023"
                    },
                    {
                        "name": "Ngày hết hạn:",
                        "content": "Thứ bảy, 16:58 20/05/2023"
                    }
                ]
            },
            "userPost": {
                "name": "Trần Thị Mỹ Nga",
                "phone": "0976990208",
                "zalo": "javascript:void(0);"
            }
        },
        {
            "header": "Bán chung cư dự án Swan Park Onsen quỹ căn hộ KĐT Ecopark tháng 5/2023",
            "address": "Địa chỉ: Swan Park Onsen Ecopark - Xã Thị trấn Văn Giang, Huyện Văn Giang, Hưng Yên",
            "attributes": [
                {
                    "price": "5.225 tỷ",
                    "acreage": "93",
                    "bedroom": "3",
                    "bathroom": "2",
                    "published": "5 giây trước"
                }
            ],
            "images": [
                "https://bds123.cdn.static123.com/images/thumbs/900x600/fit/2023/05/08/mua-ban-can-ho-swan-park-onsen-ecopark-gia-tot-3_1683539726.jpg",
                "https://bds123.cdn.static123.com/images/thumbs/900x600/fit/2023/05/08/mua-ban-can-ho-swan-park-onsen-ecopark-gia-tot-1_1683539725.jpg",
                "https://bds123.cdn.static123.com/images/thumbs/900x600/fit/2023/05/08/mua-ban-can-ho-swan-park-onsen-ecopark-gia-tot-2_1683539725.jpg"
            ],
            "sumaryPost": {
                "header": "Tóm tắt tin đăng",
                "content": "Anh/chị PKD Ecopark SĐT: 0981152882 Bán căn hộ Swan Park Onsen Ecopark, Văn Giang giá 5.225 tỷ tại Hưng Yên, diện tích: 93m2, thiết kế: 3PN- 2WC."
            },
            "description": {
                "header": "Thông tin mô tả",
                "content": "Em Dũng PKD gửi thông tin chuyển nhượng quỹ căn hộ tại dự án The Landmark - Swan Lake Onsen:  - Căn hộ Studio Swan giá 1,668 tỷ, bao gồm phí chuyển nhượng.  - Căn hộ 09 L1 - diện tích 114m², tầng cao, giá bán 7,28 tỷ bao gồm phí sang tên.  - Căn hộ 09 L2 - diện tích 114m², hướng Đông Nam - Đông Bắc, giá bán từ 7,29 tỷ (tầng thấp) đến 7,36 tỷ (tầng cao).  - Căn hộ 09 L1 tầng trung giá bán 7,680 tỷ bao gồm phí sang tên.  - Căn hộ 11 giá bán 4,25 tỷ bao gồm phí sang tên.  - Căn hộ 05 L1 giá từ 3.850 tỷ với view Quảng trường.  - Căn hộ 05A có view Quảng trường giá 5,906 tỷ.  - Căn hộ 15A L2 3 phòng ngủ với view Hồ Thiên Nga giá từ 5,225 tỷ.  - Căn hộ 2 phòng ngủ mặt sau giá từ 2,68 - 2,98 tỷ (diện tích 59m²).  - Penthouse với trần cao 4,5m/tầng (2 tầng, 9m) và diện tích từ 260 - 400m² giá từ 15,5 - 26 tỷ.  - Garden Villas với trần cao 6m, có thể làm thêm gác lửng như duplex, giá từ 3,3 - 4,5 tỷ.  ..."
            },
            "post_characteristic": {
                "header": "Đặc điểm tin đăng",
                "content": [
                    { "name": "Mã tin đăng:", "content": "647174" },
                    {
                        "name": "Khu vực:",
                        "content": "Huyện Văn Giang,  Hưng Yên"
                    },
                    { "name": "Dự án:", "content": "Swan Park Onsen Ecopark" },
                    { "name": "Gói tin:", "content": "Tin VIP 3" },
                    {
                        "name": "Ngày bắt đầu:",
                        "content": "Thứ hai, 16:55 08/05/2023"
                    },
                    {
                        "name": "Ngày hết hạn:",
                        "content": "Thứ ba, 16:55 23/05/2023"
                    }
                ]
            },
            "userPost": {
                "name": "PKD Ecopark",
                "phone": "0981152882",
                "zalo": "javascript:void(0);"
            }
        },
        {
            "header": "Bán căn hộ The Origami - Vinhomes Grand Park, giỏ hàng giá cắt lỗ siêu rẻ",
            "address": "Địa chỉ: The Origami - Vinhomes Grand Park - Đường Phước Thiện, Phường Long Thạnh Mỹ, Quận 9, Hồ Chí Minh",
            "attributes": [
                {
                    "price": "1.7 tỷ",
                    "acreage": "47",
                    "bedroom": "1",
                    "bathroom": "1",
                    "published": "9 phút trước"
                }
            ],
            "images": [
                "https://bds123.cdn.static123.com/images/thumbs/900x600/fit/2023/05/05/mua-ban-chung-cu-the-origami-vinhomes-grand-park-3_1683279882.jpg",
                "https://bds123.cdn.static123.com/images/thumbs/900x600/fit/2023/05/05/mua-ban-chung-cu-the-origami-vinhomes-grand-park-2_1683279881.jpg",
                "https://bds123.cdn.static123.com/images/thumbs/900x600/fit/2023/05/05/mua-ban-chung-cu-the-origami-vinhomes-grand-park-1_1683279881.jpg"
            ],
            "sumaryPost": {
                "header": "Tóm tắt tin đăng",
                "content": "Anh/chị Phúc Linh SĐT: 0834712768 Bán căn hộ The Origami - Vinhomes Grand Park, Quận 9 giá 1.7 tỷ tại Hồ Chí Minh, diện tích: 47m2, thiết kế: 1PN- 1WC."
            },
            "description": {
                "header": "Thông tin mô tả",
                "content": "Cập nhật giỏ hàng chuyển nhượng căn hộ giá cắt lỗ tại khu đô thị Vinhomes giá cực kỳ hấp dẫn. Quý khách nào đang tìm kiếm căn hộ với đầy đủ tiện ích tại Vinhomes để mua đầu tư hoặc ở thì đây là cơ hội tuyệt vời.  Chỉ cần đầu tư vốn ban đầu từ 15% - 25% giá trị căn hộ, anh/chị có thể sở hữu ngay nhiều căn hộ với giá cắt lỗ lên tới 20%. Giá bán của các căn hộ này không thua kém gì so với khu Rainbow.  Dưới đây là danh sách một số căn hộ rẻ mà anh/chị có thể tham khảo:  - Căn Studio: Diện tích 30m² thuộc tòa S9.02, S705, S803, S601 giá từ 1.2 tỷ.  - Căn 1PN, diện tích 36m² khu S7 giá 1.480 tỷ.  - Căn 1PN, diện tích 46.5m² thuộc tòa S9.02, S705, S8.01, S10.06, S601, S602. Giá 1.7 tỷ với view hồ bơi, 2.3 tỷ với view hồ cá Koi.  - Căn 2PN 2WC, diện tích 59.1m² các tòa S6,7,8,9,10 giá từ 2.2 tỷ - 2.5 tỷ. Căn diện tích 67.8m² giá bán 2.7 tỷ - 3 tỷ. Căn diện tích 69.5m² tòa S903, S702, S705, S10.05, S6.03, S10.06 giá bán 2.7 tỷ - 3.2 tỷ.  - Căn 3PN 2WC, diện tích 81.5m² - Giá bán từ 3 tỷ. Căn diện tích 108m² - Giá bán từ 4.2 tỷ.  Giá bán đã bao gồm các chi phí chuyển nhượng và quý khách không cần trả thêm bất kỳ chi phí nào.  Liên hệ ngay với em Linh qua số điện thoại 0834 712 768 để được tư vấn chi tiết hơn về các căn hộ này."
            },
            "post_characteristic": {
                "header": "Đặc điểm tin đăng",
                "content": [
                    { "name": "Mã tin đăng:", "content": "645126" },
                    { "name": "Khu vực:", "content": "Quận 9,  Hồ Chí Minh" },
                    {
                        "name": "Dự án:",
                        "content": "The Origami - Vinhomes Grand Park"
                    },
                    { "name": "Gói tin:", "content": "Tin VIP 3" },
                    {
                        "name": "Ngày bắt đầu:",
                        "content": "Thứ sáu, 16:46 05/05/2023"
                    },
                    {
                        "name": "Ngày hết hạn:",
                        "content": "Thứ bảy, 16:46 20/05/2023"
                    }
                ]
            },
            "userPost": {
                "name": "Phúc Linh",
                "phone": "0834712768",
                "zalo": "javascript:void(0);"
            }
        },
        {
            "header": "Bán căn hộ tại khu Aqua Bay Sky Residences giá chính chủ 2,65 tỷ động",
            "address": "Địa chỉ: Aqua Bay Sky Residences - Xã Thị trấn Văn Giang, Văn Giang, Hưng Yên",
            "attributes": [
                {
                    "price": "2.65 tỷ",
                    "acreage": "70",
                    "bedroom": "2",
                    "bathroom": "2",
                    "published": "9 phút trước"
                }
            ],
            "images": [
                "https://bds123.cdn.static123.com/images/thumbs/900x600/fit/2023/04/25/ban-can-ho-aqua-bay-sky-residences-3_1682416203.jpg",
                "https://bds123.cdn.static123.com/images/thumbs/900x600/fit/2023/04/25/ban-can-ho-aqua-bay-sky-residences-2_1682416202.jpg",
                "https://bds123.cdn.static123.com/images/thumbs/900x600/fit/2023/04/25/ban-can-ho-aqua-bay-sky-residences_1682416202.jpg",
                "https://bds123.cdn.static123.com/images/thumbs/900x600/fit/2023/04/25/ban-can-ho-aqua-bay-sky-residences-1_1682416202.jpg"
            ],
            "sumaryPost": {
                "header": "Tóm tắt tin đăng",
                "content": "Anh/chị Cao Thị Dung SĐT: 0979711768 Bán căn hộ Aqua Bay Sky Residences, Văn Giang giá 2.65 tỷ tại Hưng Yên, hướng: Tây Bắc, diện tích: 70m2, thiết kế: 2PN- 2WC."
            },
            "description": {
                "header": "Thông tin mô tả",
                "content": "- Diện tích căn hộ: 68m² với thiết kế 2 phòng ngủ và 2 phòng vệ sinh.  - Ban công hướng Đông Nam, có view đẹp nhìn thẳng mặt hồ.  - Căn hộ mới tinh và được trang bị đầy đủ nội thất cơ bản.  - Khách hàng có thể trải nghiệm cuộc sống đẳng cấp với các tiện ích nội khu. Bao gồm: công viên, hồ Thiên Nga, học viện golf, phố đi bộ, phố ẩm thực, xe bus free, ....  - Giá bán chỉ 2.6xx tỷ đồng.  - Khách hàng có thể xem căn hộ bất cứ lúc nào trong ngày và đêm.  Liên hệ để biết thêm chi tiết hoặc xem căn hộ: 0979 711 768 (em Dung)."
            },
            "post_characteristic": {
                "header": "Đặc điểm tin đăng",
                "content": [
                    { "name": "Mã tin đăng:", "content": "639402" },
                    {
                        "name": "Khu vực:",
                        "content": "Huyện Văn Giang,  Hưng Yên"
                    },
                    { "name": "Dự án:", "content": "Aqua Bay Sky Residences" },
                    { "name": "Gói tin:", "content": "Tin VIP 3" },
                    {
                        "name": "Ngày bắt đầu:",
                        "content": "Thứ ba, 16:50 25/04/2023"
                    },
                    {
                        "name": "Ngày hết hạn:",
                        "content": "Thứ tư, 16:50 10/05/2023"
                    }
                ]
            },
            "userPost": {
                "name": "Cao Thị Dung",
                "phone": "0979711768",
                "zalo": "javascript:void(0);"
            }
        },
        {
            "header": "Bán căn hộ Bình Dương tại dự án Ventoso Tower giá rẻ chỉ 1,2 tỷ đồng",
            "address": "Địa chỉ: Ventoso Tower - Đường ĐT 743C, Phường Tân Đông Hiệp, Thành Phố Dĩ An, Bình Dương",
            "attributes": [
                {
                    "price": "1.2 tỷ",
                    "acreage": "57",
                    "published": "19 phút trước"
                }
            ],
            "images": [
                "https://bds123.cdn.static123.com/images/thumbs/900x600/fit/2023/05/08/mua-ban-can-ho-ventoso-tower-gia-tot-3_1683538445.jpg",
                "https://bds123.cdn.static123.com/images/thumbs/900x600/fit/2023/05/08/mua-ban-can-ho-ventoso-tower-gia-tot-2_1683538445.jpg",
                "https://bds123.cdn.static123.com/images/thumbs/900x600/fit/2023/05/08/mua-ban-can-ho-ventoso-tower-gia-tot-1_1683538444.jpg"
            ],
            "sumaryPost": {
                "header": "Tóm tắt tin đăng",
                "content": "Anh/chị Hồ Minh Sang SĐT: 0937866991 Bán căn hộ Ventoso Tower, Dĩ An giá 1.2 tỷ tại Bình Dương, diện tích: 57m2."
            },
            "description": {
                "header": "Thông tin mô tả",
                "content": "Tòa nhà Ventoso Tower tọa lạc ở trung tâm thành phố Dĩ An, nằm sát các thành phố lân cận như TP. Thủ Đức, TP. Thuận An và TP. Biên Hoà.  Tiện ích tại Ventoso Tower bao gồm siêu thị, thư viện sách, hồ bơi và phòng tập gym. Xung quanh có đầy đủ tất cả các tiện ích trong bán kính 1km như: trường mầm non đến đại học, y tế từ cơ sở đến bệnh viện quốc tế, chợ, trung tâm thương mại, ....  Hiện tại, dự án Ventoso Tower đã hoàn thành với 2 tầng hầm và 18 tầng. Thời gian nhận cọc bắt đầu từ tháng 3/2023. Khách hàng muốn mua căn hộ tại Ventoso Tower có thể được ngân hàng Agribank chi nhánh HCM hỗ trợ cho vay tới 70% giá trị với lãi suất ưu đãi chỉ 8.5% / năm. Chỉ cần thanh toán 10% tổng giá trị (135 triệu đồng bao gồm cả VAT), khách hàng có thể ký hợp đồng mua bán để sở hữu ngay căn hộ tại trung tâm TP Dĩ An với giá tốt và vị trí cực đẹp. Khách hàng hoàn toàn yên tâm khi mua nhà bây giờ, bởi vì dự án đã bàn giao nhà ngay.  Quý khách hàng có nhu cầu xem thực tế dự án, vui lòng liên hệ số 0937 866 991 để được hỗ trợ bởi Sang."
            },
            "post_characteristic": {
                "header": "Đặc điểm tin đăng",
                "content": [
                    { "name": "Mã tin đăng:", "content": "647148" },
                    {
                        "name": "Khu vực:",
                        "content": "Thành Phố Dĩ An,  Bình Dương"
                    },
                    { "name": "Dự án:", "content": "Ventoso Tower" },
                    { "name": "Gói tin:", "content": "Tin VIP 3" },
                    {
                        "name": "Ngày bắt đầu:",
                        "content": "Thứ hai, 16:34 08/05/2023"
                    },
                    {
                        "name": "Ngày hết hạn:",
                        "content": "Thứ ba, 16:34 23/05/2023"
                    }
                ]
            },
            "userPost": {
                "name": "Hồ Minh Sang",
                "phone": "0937866991",
                "zalo": "javascript:void(0);"
            }
        },
        {
            "header": "Bán căn hộ Empire City Thủ Thiêm giá tốt, vị trí view sông, nội thất cao cấp chỉ từ 123 triệu/m2",
            "address": "Địa chỉ: Empire City Thủ Thiêm - Đường Mai Chí Thọ, Phường Thủ Thiêm, Quận 2, Hồ Chí Minh",
            "attributes": [
                {
                    "price": "19.8 tỷ",
                    "acreage": "160",
                    "bedroom": "3",
                    "bathroom": "2",
                    "published": "19 phút trước"
                }
            ],
            "images": [
                "https://bds123.cdn.static123.com/images/thumbs/900x600/fit/2023/05/03/z2531885206633-b060971c4d2312e255bb0a5958871a47_1683106279.jpg",
                "https://bds123.cdn.static123.com/images/thumbs/900x600/fit/2023/05/03/tien-ich-empire-city_1683106278.jpg",
                "https://bds123.cdn.static123.com/images/thumbs/900x600/fit/2023/05/03/nha-mau-empire-city-1-1024x636_1683106278.jpg",
                "https://bds123.cdn.static123.com/images/thumbs/900x600/fit/2023/05/03/image_1683106278.jpg"
            ],
            "sumaryPost": {
                "header": "Tóm tắt tin đăng",
                "content": "Anh/chị SĐT: Bán căn hộ Empire City Thủ Thiêm, Quận 2 giá 19.8 tỷ tại Hồ Chí Minh, diện tích: 160m2, thiết kế: 3PN- 2WC."
            },
            "description": {
                "header": "Thông tin mô tả",
                "content": "Bán căn hộ Empire City Thủ Thiêm chính chủ liên hệ nagy em Phạm Đào - 0932321228 để được hỗ trợ giá tốt.  Empire City được biết đến là dự án chung cư cao cấp được xây dựng tại khu đô thị mới Thủ Thiêm Quận 2.  Khu vực này được đánh giá là nơi có hạ tầng giao thông đồng bộ với chuỗi tiện ích dịch vụ vô cùng không hấp. Có thể đáp ứng tốt mọi nhu cầu sống của cư dân. Cụ thể gồm trường học, bệnh viện, vui chơi giải trí, trung tâm mua sắm,...  Sở hữu căn hộ Empire City, chủ sở hữu sẽ được tận hưởng chuỗi tiện ích nội khu độc đáo và trải nghiệm một không gian sống hoàn hảo.  Cụ thể căn hộ cần bán có thiết kế 3PN, tổng diện tích 160m2, căn góc sở hữu 2 view gồm công viên và sông Đồng Nai.  Khi bàn giao căn hộ, đảm bảo toàn bộ nội thất đến từ những thương hiệu cao cấp, đạt tiêu chuẩn 5 sao quốc tế.  Khách hàng có thể xem nhà, nếu ưng ý chốt ngay để có thể thương lượng giá cả hợp lý."
            },
            "post_characteristic": {
                "header": "Đặc điểm tin đăng",
                "content": [
                    { "name": "Mã tin đăng:", "content": "643692" },
                    { "name": "Khu vực:", "content": "Quận 2,  Hồ Chí Minh" },
                    { "name": "Dự án:", "content": "Empire City Thủ Thiêm" },
                    { "name": "Gói tin:", "content": "Tin VIP 3" },
                    {
                        "name": "Ngày bắt đầu:",
                        "content": "Thứ tư, 16:31 03/05/2023"
                    },
                    {
                        "name": "Ngày hết hạn:",
                        "content": "Thứ bảy, 16:31 13/05/2023"
                    }
                ]
            },
            "userPost": {
                "name": "",
                "phone": "",
                "zalo": "javascript:void(0);"
            }
        },
        {
            "header": "Bán căn hộ Elysian giá tốt, ưu đãi hấp dẫn, tầm nhìn đắt giá chỉ từ 51 triệu/m2 liên hệ 0932338963",
            "address": "Địa chỉ: Elysian - 170 Đường Lò Lu, Phường Trường Thạnh, Quận 9, Hồ Chí Minh",
            "attributes": [
                {
                    "price": "4 tỷ",
                    "acreage": "77",
                    "bedroom": "2",
                    "bathroom": "2",
                    "published": "19 phút trước"
                }
            ],
            "images": [
                "https://bds123.cdn.static123.com/images/thumbs/900x600/fit/2023/05/03/tien-ich-can-ho-elysian-thu-duc-gamuda-land-9_1683106782.jpg",
                "https://bds123.cdn.static123.com/images/thumbs/900x600/fit/2023/05/03/337030939-732348961692149-6608704938690503642-n-1_1683106779.jpg",
                "https://bds123.cdn.static123.com/images/thumbs/900x600/fit/2023/05/03/thiet-ke-can-ho-elysian_1683106782.jpg",
                "https://bds123.cdn.static123.com/images/thumbs/900x600/fit/2023/05/03/sp-mo-ban-elysian-lo-lu-1_1683106781.png"
            ],
            "sumaryPost": {
                "header": "Tóm tắt tin đăng",
                "content": "Anh/chị Huyền Hòa SĐT: 0932338963 Bán căn hộ Elysian, Quận 9 giá 4 tỷ tại Hồ Chí Minh, diện tích: 77m2, thiết kế: 2PN- 2WC."
            },
            "description": {
                "header": "Thông tin mô tả",
                "content": "Bán căn hộ Elysian tại Lò Lu, P. Trường Thạnh, Quận 9.  Elysian được biết đến là dự án chung cư do Gamuda Land làm chủ đầu tư. Dự án được đầu tư và thiết kế với nhiều phong cách độc đáo. Hướng đến nhu cầu thị hiếu người dùng hiện nay.  Đến với Elysian, ngoài trải nghiệm các tiện ích dịch vụ hiện đại. Quý cư dân có thể ngắm nhìn và tận hưởng không gian sống xanh, môi trường thoáng mát được chủ đầu tư thiết kế và bố trí tại tầng trệt, tầng trung, tầng thượng và ban công căn hộ.  Hiện dự án chung cư Elysian đang mở bán một vài căn hộ tại tòa A, giá gốc chiết khấu cao dao động từ 5 - 65% cho sang nhượng và mua căn hộ ở ngay.  Thời gian dự kiến bàn giao dự án vào cuối năm 2025.  Mua ngay căn hộ Elysian giá tốt gặp em Huyền Hòa - 0932338963"
            },
            "post_characteristic": {
                "header": "Đặc điểm tin đăng",
                "content": [
                    { "name": "Mã tin đăng:", "content": "643694" },
                    { "name": "Khu vực:", "content": "Quận 9,  Hồ Chí Minh" },
                    { "name": "Dự án:", "content": "Elysian" },
                    { "name": "Gói tin:", "content": "Tin VIP 3" },
                    {
                        "name": "Ngày bắt đầu:",
                        "content": "Thứ tư, 16:39 03/05/2023"
                    },
                    {
                        "name": "Ngày hết hạn:",
                        "content": "Thứ bảy, 16:39 13/05/2023"
                    }
                ]
            },
            "userPost": {
                "name": "Huyền Hòa",
                "phone": "0932338963",
                "zalo": "javascript:void(0);"
            }
        },
        {
            "header": "Bán căn hộ Midori Park The Glory giá chính chủ từ chủ đầu tư Becamex chỉ 2,3 tỷ",
            "address": "Địa chỉ: Midori Park The Glory - Phường Hòa Phú, Thành Phố Thủ Dầu Một, Bình Dương",
            "attributes": [
                {
                    "price": "2.3 tỷ",
                    "acreage": "69",
                    "published": "29 phút trước"
                }
            ],
            "images": [
                "https://bds123.cdn.static123.com/images/thumbs/900x600/fit/2023/04/24/ban-can-ho-midori-park-the-glory-2_1682327974.jpg",
                "https://bds123.cdn.static123.com/images/thumbs/900x600/fit/2023/04/24/ban-can-ho-midori-park-the-glory-1_1682327973.jpg",
                "https://bds123.cdn.static123.com/images/thumbs/900x600/fit/2023/04/24/ban-can-ho-midori-park-the-glory_1682327974.jpg"
            ],
            "sumaryPost": {
                "header": "Tóm tắt tin đăng",
                "content": "Anh/chị Nguyễn Phạm Tú Trinh SĐT: 0933750960 Bán căn hộ Midori Park The Glory, Thủ Dầu Một giá 2.3 tỷ tại Bình Dương, diện tích: 69m2."
            },
            "description": {
                "header": "Thông tin mô tả",
                "content": "Midori Park The Glory là dự án căn hộ resort đầu tiên tại Thành phố Mới Bình Dương. Sở hữu một trong những thác nước nhân tạo lớn nhất tại Việt Nam cùng nhiều tiện ích nội khu nổi trội, đáp ứng mọi nhu cầu của cư dân. Đặc biệt, hứa hẹn sẽ mang đến không gian sống cao cấp ngay tại nhà.  Midori Park The Glory là nơi tuyệt vời để trải nghiệm cuộc sống hoàn hảo. Với hồ bơi vô cực, phòng tập gym, sân tennis, vườn thiền, vườn nướng trên cao, sân chơi trẻ em, cổng trời skydeck và con đường xanh dọc theo dự án, cư dân sẽ được hưởng thụ không gian sống tuyệt vời và giải trí đầy đủ.  Với giá bán chỉ từ 34 triệu đồng/m2, Midori Park The Glory Bình Dương đang là dự án căn hộ được rất nhiều người quan tâm. Không chỉ với giá bán hợp lý, dự án còn hỗ trợ thanh toán trong 2 năm không lãi suất và đưa ra các gói thanh toán linh hoạt.  Midori Park The Glory Bình Dương cũng hỗ trợ vay vốn đến 70% trong 20 năm, giúp khách hàng dễ dàng sở hữu căn hộ mơ ước.  Dự án Midori Park The Glory sẽ bàn giao vào tháng 04/2024. Để biết thêm thông tin về dự án và được tư vấn, vui lòng liên hệ với nhân viên chủ đầu tư Trinh qua số điện thoại 0933 750 960. Hãy nhanh tay đăng ký để sở hữu ngay căn hộ tại Midori Park The Glory Bình Dương và trải nghiệm cuộc sống tuyệt vời!"
            },
            "post_characteristic": {
                "header": "Đặc điểm tin đăng",
                "content": [
                    { "name": "Mã tin đăng:", "content": "638477" },
                    {
                        "name": "Khu vực:",
                        "content": "Thành Phố Thủ Dầu Một,  Bình Dương"
                    },
                    { "name": "Dự án:", "content": "Midori Park The Glory" },
                    { "name": "Gói tin:", "content": "Tin VIP 3" },
                    {
                        "name": "Ngày bắt đầu:",
                        "content": "Thứ hai, 16:20 24/04/2023"
                    },
                    {
                        "name": "Ngày hết hạn:",
                        "content": "Thứ ba, 16:20 09/05/2023"
                    }
                ]
            },
            "userPost": {
                "name": "Nguyễn Phạm Tú Trinh",
                "phone": "0933750960",
                "zalo": "javascript:void(0);"
            }
        }
    ]
}
